LICENSE.txt
MANIFEST.in
README.rst
setup.py
src/ghdiff.py
src/tests.py
src/ghdiff_class.egg-info/PKG-INFO
src/ghdiff_class.egg-info/SOURCES.txt
src/ghdiff_class.egg-info/dependency_links.txt
src/ghdiff_class.egg-info/requires.txt
src/ghdiff_class.egg-info/top_level.txt