Metadata-Version: 1.0
Name: ghdiff-class
Version: 0.1
Summary: Generate pretty Github-style diffs (class version, see ghdiff for origin)
Home-page: http://github/twidi/ghdiff
Author: Stephane 'Twidi' Angel
Author-email: s.angel@twidi.com
License: MIT
Platform: UNKNOWN
